darmok/__init__.py
darmok-0.0.1.dist-info/LICENSE
darmok-0.0.1.dist-info/METADATA
darmok-0.0.1.dist-info/WHEEL
darmok-0.0.1.dist-info/top_level.txt
darmok-0.0.1.dist-info/RECORD
