Metadata-Version: 2.1
Name: darmok
Version: 0.0.1
Summary: Generic data analytics library
Home-page: https://github.com/gino-serpa/darmok.git
Author: gino serpa
Author-email: gino.serpa@gmail.com
License: UNKNOWN
Platform: UNKNOWN
Classifier: Programming Language :: Python :: 3
Classifier: License :: OSI Approved :: MIT License
Classifier: Operating System :: OS Independent
Requires-Python: >=3.6
